{
	"name": "layer by operation",
	"versions": {
		"attack": "15",
		"navigator": "5.0.1",
		"layer": "4.5"
	},
	"domain": "enterprise-attack",
	"description": "",
	"filters": {
		"platforms": [
			"Windows",
			"Linux",
			"macOS",
			"Network",
			"PRE",
			"Containers",
			"Office 365",
			"SaaS",
			"Google Workspace",
			"IaaS",
			"Azure AD"
		]
	},
	"sorting": 0,
	"layout": {
		"layout": "side",
		"aggregateFunction": "average",
		"showID": false,
		"showName": true,
		"showAggregateScores": false,
		"countUnscored": false,
		"expandedSubtechniques": "none"
	},
	"hideDisabled": false,
	"techniques": [
		{
			"techniqueID": "T1557",
			"tactic": "credential-access",
			"score": 1,
			"color": "",
			"comment": "",
			"enabled": true,
			"metadata": [],
			"links": [],
			"showSubtechniques": false
		},
		{
			"techniqueID": "T1557",
			"tactic": "collection",
			"score": 1,
			"color": "",
			"comment": "",
			"enabled": true,
			"metadata": [],
			"links": [],
			"showSubtechniques": false
		},
		{
			"techniqueID": "T1583",
			"tactic": "resource-development",
			"score": 2,
			"color": "",
			"comment": "",
			"enabled": true,
			"metadata": [],
			"links": [],
			"showSubtechniques": false
		},
		{
			"techniqueID": "T1071",
			"tactic": "command-and-control",
			"score": 1,
			"color": "",
			"comment": "",
			"enabled": true,
			"metadata": [],
			"links": [],
			"showSubtechniques": false
		},
		{
			"techniqueID": "T1659",
			"tactic": "initial-access",
			"score": 3,
			"color": "",
			"comment": "",
			"enabled": true,
			"metadata": [],
			"links": [],
			"showSubtechniques": false
		},
		{
			"techniqueID": "T1659",
			"tactic": "command-and-control",
			"score": 3,
			"color": "",
			"comment": "",
			"enabled": true,
			"metadata": [],
			"links": [],
			"showSubtechniques": false
		},
		{
			"techniqueID": "T1010",
			"tactic": "discovery",
			"score": 2,
			"color": "",
			"comment": "",
			"enabled": true,
			"metadata": [],
			"links": [],
			"showSubtechniques": false
		},
		{
			"techniqueID": "T1092",
			"tactic": "command-and-control",
			"score": 2,
			"color": "",
			"comment": "",
			"enabled": true,
			"metadata": [],
			"links": [],
			"showSubtechniques": false
		},
		{
			"techniqueID": "T1595",
			"tactic": "reconnaissance",
			"score": 3,
			"color": "",
			"comment": "",
			"enabled": true,
			"metadata": [],
			"links": [],
			"showSubtechniques": false
		},
		{
			"techniqueID": "T1548",
			"tactic": "privilege-escalation",
			"score": 1,
			"color": "",
			"comment": "",
			"enabled": true,
			"metadata": [],
			"links": [],
			"showSubtechniques": false
		},
		{
			"techniqueID": "T1548",
			"tactic": "defense-evasion",
			"score": 1,
			"color": "",
			"comment": "",
			"enabled": true,
			"metadata": [],
			"links": [],
			"showSubtechniques": false
		},
		{
			"techniqueID": "T1087",
			"tactic": "discovery",
			"score": 1,
			"color": "",
			"comment": "",
			"enabled": true,
			"metadata": [],
			"links": [],
			"showSubtechniques": false
		},
		{
			"techniqueID": "T1059",
			"tactic": "execution",
			"score": 2,
			"color": "",
			"comment": "",
			"enabled": true,
			"metadata": [],
			"links": [],
			"showSubtechniques": false
		},
		{
			"techniqueID": "T1020",
			"tactic": "exfiltration",
			"score": 3,
			"color": "",
			"comment": "",
			"enabled": true,
			"metadata": [],
			"links": [],
			"showSubtechniques": false
		},
		{
			"techniqueID": "T1210",
			"tactic": "lateral-movement",
			"score": 2,
			"color": "",
			"comment": "",
			"enabled": true,
			"metadata": [],
			"links": [],
			"showSubtechniques": false
		},
		{
			"techniqueID": "T1098",
			"tactic": "persistence",
			"score": 2,
			"color": "",
			"comment": "",
			"enabled": true,
			"metadata": [],
			"links": [],
			"showSubtechniques": false
		},
		{
			"techniqueID": "T1098",
			"tactic": "privilege-escalation",
			"score": 2,
			"color": "",
			"comment": "",
			"enabled": true,
			"metadata": [],
			"links": [],
			"showSubtechniques": false
		},
		{
			"techniqueID": "T1531",
			"tactic": "impact",
			"score": 1,
			"color": "",
			"comment": "",
			"enabled": true,
			"metadata": [],
			"links": [],
			"showSubtechniques": false
		},
		{
			"techniqueID": "T1650",
			"tactic": "resource-development",
			"score": 1,
			"color": "",
			"comment": "",
			"enabled": true,
			"metadata": [],
			"links": [],
			"showSubtechniques": false
		},
		{
			"techniqueID": "T1651",
			"tactic": "execution",
			"score": 1,
			"color": "",
			"comment": "",
			"enabled": true,
			"metadata": [],
			"links": [],
			"showSubtechniques": false
		},
		{
			"techniqueID": "T1134",
			"tactic": "defense-evasion",
			"score": 2,
			"color": "",
			"comment": "",
			"enabled": true,
			"metadata": [],
			"links": [],
			"showSubtechniques": false
		},
		{
			"techniqueID": "T1134",
			"tactic": "privilege-escalation",
			"score": 2,
			"color": "",
			"comment": "",
			"enabled": true,
			"metadata": [],
			"links": [],
			"showSubtechniques": false
		}
	],
	"gradient": {
		"colors": [
			"#ff6666ff",
			"#ffe766ff",
			"#8ec843ff"
		],
		"minValue": 1,
		"maxValue": 3
	},
	"legendItems": [],
	"metadata": [],
	"links": [],
	"showTacticRowBackground": false,
	"tacticRowBackground": "#dddddd",
	"selectTechniquesAcrossTactics": true,
	"selectSubtechniquesWithParent": false,
	"selectVisibleTechniques": false
}